MANIFEST.in
README
README.md
setup.py
webdiff/__init__.py
webdiff/app.py
webdiff/argparser.py
webdiff/diff.py
webdiff/dirdiff.py
webdiff/github_fetcher.py
webdiff/githubdiff.py
webdiff/gitwebdiff.py
webdiff/localfilediff.py
webdiff/util.py
webdiff/static/__init__.py
webdiff/static/__pycache__/__init__.cpython-39.pyc
webdiff/static/codediff.js/codediff.css
webdiff/static/codediff.js/codediff.js
webdiff/static/codediff.js/difflib.js
webdiff/static/codediff.js/googlecode.css
webdiff/static/css/googlecode.css
webdiff/static/css/inconsolata.css
webdiff/static/css/style.css
webdiff/static/css/Inconsolata/Inconsolata-Bold.ttf
webdiff/static/css/Inconsolata/Inconsolata-Regular.ttf
webdiff/static/css/Inconsolata/OFL.txt
webdiff/static/img/favicon.ico
webdiff/static/img/sprites.png
webdiff/static/img/trans_bg.gif
webdiff/static/js/file_diff.js
webdiff/static/js/highlight.pack.min.js
webdiff/static/js/jquery-2.1.1.min.js
webdiff/templates/__init__.py
webdiff/templates/base.html
webdiff/templates/file_diff.html
webdiff/templates/__pycache__/__init__.cpython-39.pyc
webdiff_for_coi.egg-info/PKG-INFO
webdiff_for_coi.egg-info/SOURCES.txt
webdiff_for_coi.egg-info/dependency_links.txt
webdiff_for_coi.egg-info/entry_points.txt
webdiff_for_coi.egg-info/requires.txt
webdiff_for_coi.egg-info/top_level.txt