Metadata-Version: 2.1
Name: webdiff-for-coi
Version: 0.15.7
Summary: Two-column web-based git difftool
Home-page: https://github.com/song-fangzhen/webdiff-for-coi/
Author: Fangzhen Song
Author-email: songfangzhen@bytedance.com
License: UNKNOWN
Download-URL: https://github.com/song-fangzhen/webdiff-for-coi/archive/refs/tags/v0.15.7.tar.gz
Platform: UNKNOWN
Classifier: Environment :: Console
Classifier: Environment :: Web Environment
Classifier: Framework :: Flask
Classifier: Development Status :: 4 - Beta
Classifier: Intended Audience :: Developers
Classifier: License :: OSI Approved :: Apache Software License
Classifier: Topic :: Software Development :: Version Control
